{
  "entries": {
    "tap": {
      "homebrew/cask": {
        "revision": "78b7f19c5c19b4d1289cb41ae564c99a2ab45afc"
      },
      "neovim/neovim": {
        "revision": "e587b5c90456a895a11bc5ae81e5cfdde6b23dd4"
      },
      "d12frosted/emacs-plus": {
        "revision": "1f4fb6b41f4e3322050e16dac10e896a117affaf"
      },
      "universal-ctags/universal-ctags": {
        "revision": "a63986ba838043d651d09e3ab6de70388eeaf876"
      },
      "tankerhq/repo": {
        "revision": "c614179b20a4ae2074e302dc15c388179f6309e7"
      },
      "caskroom/drivers": {
        "revision": "da9a2adc142d021a9204b5cf0f672a3be9b5a396"
      }
    },
    "brew": {
      "mas": {
        "version": "1.6.3",
        "bottle": {
          "cellar": ":any",
          "prefix": "/usr/local",
          "files": {
            "catalina": {
              "url": "https://homebrew.bintray.com/bottles/mas-1.6.3.catalina.bottle.tar.gz",
              "sha256": "2069b8c1c1a64c2fb91cc1c25ab9c9890c61f2182224b9e0605a35a151bb85bd"
            },
            "mojave": {
              "url": "https://homebrew.bintray.com/bottles/mas-1.6.3.mojave.bottle.tar.gz",
              "sha256": "3dd5a50b551a37c164c31375cc8498ba870e29e50086bd5c4c294bc26708a6d2"
            },
            "high_sierra": {
              "url": "https://homebrew.bintray.com/bottles/mas-1.6.3.high_sierra.bottle.tar.gz",
              "sha256": "a0d1e45203448c08420c3eab2d40ef957fd22c8e40fbeb067bc7bffe4f08dfe2"
            }
          }
        }
      },
      "git": {
        "version": "2.26.0",
        "bottle": {
          "cellar": "/usr/local/Cellar",
          "prefix": "/usr/local",
          "files": {
            "catalina": {
              "url": "https://homebrew.bintray.com/bottles/git-2.26.0.catalina.bottle.tar.gz",
              "sha256": "174f1f2513dfc0be1997c4385cc4579c37479aa1038e5f73088fb0a1edfbe5e9"
            },
            "mojave": {
              "url": "https://homebrew.bintray.com/bottles/git-2.26.0.mojave.bottle.tar.gz",
              "sha256": "872641963bc853b4e421a0d8fa3a535812fc1a81d07fe00cbd8b1f35bc66558c"
            },
            "high_sierra": {
              "url": "https://homebrew.bintray.com/bottles/git-2.26.0.high_sierra.bottle.tar.gz",
              "sha256": "d811df72427c53248ef4ba9e954ecd998c9b72cae87c620af37fa0813e0a0a5f"
            }
          }
        }
      },
      "zsh": {
        "version": "5.8",
        "bottle": {
          "cellar": "/usr/local/Cellar",
          "prefix": "/usr/local",
          "files": {
            "catalina": {
              "url": "https://homebrew.bintray.com/bottles/zsh-5.8.catalina.bottle.tar.gz",
              "sha256": "209d04a4d62f6162f1b6cf824d2c50b00b52cb812c04c1967e5b376573b5aef0"
            },
            "mojave": {
              "url": "https://homebrew.bintray.com/bottles/zsh-5.8.mojave.bottle.tar.gz",
              "sha256": "c5c35657637c97132efbaa0fd8e2add568aaa62adfe66e7d19f961f8e9506da9"
            },
            "high_sierra": {
              "url": "https://homebrew.bintray.com/bottles/zsh-5.8.high_sierra.bottle.tar.gz",
              "sha256": "029b8c6922f01bfd832dd0f4f940f99328d2495714c37c1dc7ef326d6fb1459e"
            }
          }
        }
      },
      "make": {
        "version": "4.3",
        "bottle": {
          "cellar": "/usr/local/Cellar",
          "prefix": "/usr/local",
          "files": {
            "catalina": {
              "url": "https://homebrew.bintray.com/bottles/make-4.3.catalina.bottle.tar.gz",
              "sha256": "b2cbb6b854495469de4d065825c94540ad3053a1ff7c1832f4eb7781ee6b8231"
            },
            "mojave": {
              "url": "https://homebrew.bintray.com/bottles/make-4.3.mojave.bottle.tar.gz",
              "sha256": "50ac9c7185e08349c35531d8ee30e755713aec340229cab2008ba1a2ceac15c9"
            },
            "high_sierra": {
              "url": "https://homebrew.bintray.com/bottles/make-4.3.high_sierra.bottle.tar.gz",
              "sha256": "e7f49884dbeaae3e7ccc9dc3a58fec587c2a594f50314dbc33cde44c6f807f53"
            }
          }
        }
      },
      "neovim": {
        "version": "0.4.3",
        "bottle": {
          "cellar": "/usr/local/Cellar",
          "prefix": "/usr/local",
          "files": {
            "catalina": {
              "url": "https://homebrew.bintray.com/bottles/neovim-0.4.3.catalina.bottle.tar.gz",
              "sha256": "389ab254794ea04df8a106bf281c227c4fdee27c609d52951f32b9a0239031d6"
            },
            "mojave": {
              "url": "https://homebrew.bintray.com/bottles/neovim-0.4.3.mojave.bottle.tar.gz",
              "sha256": "fb6cc38c45be4650a4a750a314cec27f6f7643dc7c22a1f5abae347e1b39b388"
            },
            "high_sierra": {
              "url": "https://homebrew.bintray.com/bottles/neovim-0.4.3.high_sierra.bottle.tar.gz",
              "sha256": "b2f7450e005f4eb22bfaf650fe7741fa8629393a947b4dd48c9f91e7fc258113"
            }
          }
        }
      },
      "emacs-plus": {
        "version": "26.3",
        "bottle": {
          "cellar": "/usr/local/Cellar",
          "prefix": "/usr/local",
          "files": {
            "mojave": {
              "url": "https://dl.bintray.com/d12frosted/emacs-plus/emacs-plus-26.3.mojave.bottle.tar.gz",
              "sha256": "6b59ea5c941b754f5008039be319e4437ebd66dc2e1a50fdf890cf226c078386"
            },
            "catalina": {
              "url": "https://dl.bintray.com/d12frosted/emacs-plus/emacs-plus-26.3.catalina.bottle.tar.gz",
              "sha256": "cb589861c8a697869107d1cbacc9cc920a8e7257b5c371b7e590b05e7e04c92c"
            }
          }
        },
        "options": {
          "args": [
            "HEAD",
            "with-modern-icon",
            "without-spacemacs-icon"
          ]
        }
      },
      "openssl": {
        "version": "1.0.2t",
        "bottle": null
      },
      "coreutils": {
        "version": "8.32",
        "bottle": {
          "cellar": "/usr/local/Cellar",
          "prefix": "/usr/local",
          "files": {
            "catalina": {
              "url": "https://homebrew.bintray.com/bottles/coreutils-8.32.catalina.bottle.tar.gz",
              "sha256": "67a4452d75a1882bd7fb977b384204edfa2758276d66290e595487922368e093"
            },
            "mojave": {
              "url": "https://homebrew.bintray.com/bottles/coreutils-8.32.mojave.bottle.tar.gz",
              "sha256": "5da6cb9dbc0a8144480dde2fb78eb0a5a1710490afc3697174f7e261ec69763f"
            },
            "high_sierra": {
              "url": "https://homebrew.bintray.com/bottles/coreutils-8.32.high_sierra.bottle.tar.gz",
              "sha256": "caa8cd8965727d0e805eccdc3e306cd0599720cdd0d5417cfcca03bead670663"
            }
          }
        }
      },
      "gnu-tar": {
        "version": "1.32",
        "bottle": {
          "cellar": ":any_skip_relocation",
          "prefix": "/usr/local",
          "files": {
            "catalina": {
              "url": "https://homebrew.bintray.com/bottles/gnu-tar-1.32.catalina.bottle.1.tar.gz",
              "sha256": "158cb67ea9e02435d671013b4d0d7369822758d9f7ff400ce2512a03f2f7f4e4"
            },
            "mojave": {
              "url": "https://homebrew.bintray.com/bottles/gnu-tar-1.32.mojave.bottle.1.tar.gz",
              "sha256": "1034894e78bb22b0fcf0c8114666d4dc3eb82345a5ca83797ca3bda367d998ac"
            },
            "high_sierra": {
              "url": "https://homebrew.bintray.com/bottles/gnu-tar-1.32.high_sierra.bottle.1.tar.gz",
              "sha256": "3771cead286229786d9d92a7697bc6e0de576ec9cae1f881017884ceb3e24f17"
            }
          }
        }
      },
      "fzf": {
        "version": "0.21.1",
        "bottle": {
          "cellar": ":any_skip_relocation",
          "prefix": "/usr/local",
          "files": {
            "catalina": {
              "url": "https://homebrew.bintray.com/bottles/fzf-0.21.1.catalina.bottle.tar.gz",
              "sha256": "733f79496c3246979ca05eeb5677a5fd9e8ec532e69e8b2012102cacddba8ae6"
            },
            "mojave": {
              "url": "https://homebrew.bintray.com/bottles/fzf-0.21.1.mojave.bottle.tar.gz",
              "sha256": "3c03bb9715be153a0f776d06cf4acd436ad4faa4266f7bd875a0d37594291516"
            },
            "high_sierra": {
              "url": "https://homebrew.bintray.com/bottles/fzf-0.21.1.high_sierra.bottle.tar.gz",
              "sha256": "d15a616156eb92071f1cfc50f10366532af92ca1635d309162141ad67f785865"
            }
          }
        }
      },
      "reattach-to-user-namespace": {
        "version": "2.8",
        "bottle": {
          "cellar": ":any_skip_relocation",
          "prefix": "/usr/local",
          "files": {
            "catalina": {
              "url": "https://homebrew.bintray.com/bottles/reattach-to-user-namespace-2.8.catalina.bottle.tar.gz",
              "sha256": "165edabd70a4acbdee2f3e09e9a37e9ca23b2d485ebe12d62511cef9c45fd757"
            },
            "mojave": {
              "url": "https://homebrew.bintray.com/bottles/reattach-to-user-namespace-2.8.mojave.bottle.tar.gz",
              "sha256": "388e45300bf6cf3888a490878c9a03b97c06a52fe316a18d099ab97bddbed295"
            },
            "high_sierra": {
              "url": "https://homebrew.bintray.com/bottles/reattach-to-user-namespace-2.8.high_sierra.bottle.tar.gz",
              "sha256": "adc59ad02ccf302e9c71c08d10a4eb95d5d210dbfebe9a00b41648b094c96f09"
            },
            "sierra": {
              "url": "https://homebrew.bintray.com/bottles/reattach-to-user-namespace-2.8.sierra.bottle.tar.gz",
              "sha256": "1ec537d4be63bbcdaf3644506d0b272051fd2617db84c111152a33d8d0184339"
            }
          }
        }
      },
      "tmux": {
        "version": "3.0a_1",
        "bottle": {
          "cellar": ":any",
          "prefix": "/usr/local",
          "files": {
            "catalina": {
              "url": "https://homebrew.bintray.com/bottles/tmux-3.0a_1.catalina.bottle.tar.gz",
              "sha256": "d83b378969a8af595451db10bf4b8eb251a8ed4217cb13e161b3dbe20330d1f8"
            },
            "mojave": {
              "url": "https://homebrew.bintray.com/bottles/tmux-3.0a_1.mojave.bottle.tar.gz",
              "sha256": "4acca70a1bba7bb762081015373c438a930af6a6b28e9e1409c4b84ae78ad514"
            },
            "high_sierra": {
              "url": "https://homebrew.bintray.com/bottles/tmux-3.0a_1.high_sierra.bottle.tar.gz",
              "sha256": "bc934e88baba7f0549c3b5916ed19211764ecaf6c95e46624c2f641b631abdb9"
            }
          }
        }
      },
      "ripgrep": {
        "version": "12.0.1",
        "bottle": {
          "cellar": ":any",
          "prefix": "/usr/local",
          "files": {
            "catalina": {
              "url": "https://homebrew.bintray.com/bottles/ripgrep-12.0.1.catalina.bottle.tar.gz",
              "sha256": "61b5686741206e584aa2f94746ecdd68bea29ad381b2a6c0ce2076cacb8408ca"
            },
            "mojave": {
              "url": "https://homebrew.bintray.com/bottles/ripgrep-12.0.1.mojave.bottle.tar.gz",
              "sha256": "1203664c55ee33d9b668cc9e8f4fe06b2cfe48ae7bc1374b3576104defc279ac"
            },
            "high_sierra": {
              "url": "https://homebrew.bintray.com/bottles/ripgrep-12.0.1.high_sierra.bottle.tar.gz",
              "sha256": "7a0ff676fe9bfc33f3c4279856c45238e3cc61a396cbd5e266d23796a5003e72"
            }
          }
        }
      },
      "direnv": {
        "version": "2.21.2",
        "bottle": {
          "cellar": ":any_skip_relocation",
          "prefix": "/usr/local",
          "files": {
            "catalina": {
              "url": "https://homebrew.bintray.com/bottles/direnv-2.21.2.catalina.bottle.tar.gz",
              "sha256": "31a7b6b1f16dd3e881ec693cb83e07757500f8d4810a5ebad3ab5986f7a6ef28"
            },
            "mojave": {
              "url": "https://homebrew.bintray.com/bottles/direnv-2.21.2.mojave.bottle.tar.gz",
              "sha256": "6a79378f41555b964e95c093c4a693fd2252c873bae453ebb309ec148eaeac7b"
            },
            "high_sierra": {
              "url": "https://homebrew.bintray.com/bottles/direnv-2.21.2.high_sierra.bottle.tar.gz",
              "sha256": "e490c0f7a242c35343e2f4d108b069380a9f73b2c7656d23db1c8940e549920b"
            }
          }
        }
      },
      "youtube-dl": {
        "version": "2020.03.24",
        "bottle": false
      },
      "wget": {
        "version": "1.20.3_2",
        "bottle": {
          "cellar": "/usr/local/Cellar",
          "prefix": "/usr/local",
          "files": {
            "catalina": {
              "url": "https://homebrew.bintray.com/bottles/wget-1.20.3_2.catalina.bottle.tar.gz",
              "sha256": "ef65c759c5097a36323fa9c77756468649e8d1980a3a4e05695c05e39568967c"
            },
            "mojave": {
              "url": "https://homebrew.bintray.com/bottles/wget-1.20.3_2.mojave.bottle.tar.gz",
              "sha256": "28f4090610946a4eb207df102d841de23ced0d06ba31cb79e040d883906dcd4f"
            },
            "high_sierra": {
              "url": "https://homebrew.bintray.com/bottles/wget-1.20.3_2.high_sierra.bottle.tar.gz",
              "sha256": "91dd0caca9bd3f38c439d5a7b6f68440c4274945615fae035ff0a369264b8a2f"
            }
          }
        }
      },
      "curl": {
        "version": "7.69.1",
        "bottle": {
          "cellar": ":any",
          "prefix": "/usr/local",
          "files": {
            "catalina": {
              "url": "https://homebrew.bintray.com/bottles/curl-7.69.1.catalina.bottle.tar.gz",
              "sha256": "400500fede02f9335bd38c16786b2bbf5e601e358dfac8c21e363d2a8fdd8fac"
            },
            "mojave": {
              "url": "https://homebrew.bintray.com/bottles/curl-7.69.1.mojave.bottle.tar.gz",
              "sha256": "f082c275f9af1e8e93be12b63a1aff659ba6efa48c8528a97e26c9858a6f95b6"
            },
            "high_sierra": {
              "url": "https://homebrew.bintray.com/bottles/curl-7.69.1.high_sierra.bottle.tar.gz",
              "sha256": "ad023093c252799a4c60646a149bfe14ffa6984817cf463a6f0e98f6551057fe"
            }
          }
        }
      },
      "gnu-sed": {
        "version": "4.8",
        "bottle": {
          "cellar": ":any_skip_relocation",
          "prefix": "/usr/local",
          "files": {
            "catalina": {
              "url": "https://homebrew.bintray.com/bottles/gnu-sed-4.8.catalina.bottle.tar.gz",
              "sha256": "726be75d6d7155820b408a10e5c1a5ba1406374a7fc167af62524a4f4bbbc099"
            },
            "mojave": {
              "url": "https://homebrew.bintray.com/bottles/gnu-sed-4.8.mojave.bottle.tar.gz",
              "sha256": "093f16752e7dfb115c055f20aed090108b94edd47c40f5e50878d961359251b2"
            },
            "high_sierra": {
              "url": "https://homebrew.bintray.com/bottles/gnu-sed-4.8.high_sierra.bottle.tar.gz",
              "sha256": "865abe618c67037a4a419a05e0df2c6814fb3abdd6f631ea546aeba0aaf8eb78"
            }
          }
        },
        "options": {
          "args": [
            "with-default-names"
          ]
        }
      },
      "z": {
        "version": "1.11",
        "bottle": false
      },
      "cloc": {
        "version": "1.84",
        "bottle": {
          "cellar": ":any_skip_relocation",
          "prefix": "/usr/local",
          "files": {
            "catalina": {
              "url": "https://homebrew.bintray.com/bottles/cloc-1.84.catalina.bottle.1.tar.gz",
              "sha256": "efc3757be2925b654cc317cc7f28dd3b8a7af83898cba21ce2dd48e47a3d642b"
            },
            "mojave": {
              "url": "https://homebrew.bintray.com/bottles/cloc-1.84.mojave.bottle.1.tar.gz",
              "sha256": "d3ef73f5832515c2b6500815826e1f5ac172a62c2079e503dd9fee92433b236d"
            },
            "high_sierra": {
              "url": "https://homebrew.bintray.com/bottles/cloc-1.84.high_sierra.bottle.1.tar.gz",
              "sha256": "0eedafaa2a69493f39b0ea619ecbb5193a55a3519a0c5c914fc75700510b2394"
            }
          }
        }
      },
      "terraform": {
        "version": "0.12.24",
        "bottle": {
          "cellar": ":any_skip_relocation",
          "prefix": "/usr/local",
          "files": {
            "catalina": {
              "url": "https://homebrew.bintray.com/bottles/terraform-0.12.24.catalina.bottle.tar.gz",
              "sha256": "cdfb0e90156ee1bedb30f52a9e260340ff7c08580c12dd35138bf63c01fe1000"
            },
            "mojave": {
              "url": "https://homebrew.bintray.com/bottles/terraform-0.12.24.mojave.bottle.tar.gz",
              "sha256": "2a21a77589673b2064c9fa7587a79a0375d69a8e02f824e5dc22dc960bf2d78b"
            },
            "high_sierra": {
              "url": "https://homebrew.bintray.com/bottles/terraform-0.12.24.high_sierra.bottle.tar.gz",
              "sha256": "1eefeff3899922cc643b82dcc8fec52ce9ea65fd789a73639588e6123239fa0c"
            }
          }
        }
      },
      "jq": {
        "version": "1.6",
        "bottle": {
          "cellar": ":any",
          "prefix": "/usr/local",
          "files": {
            "catalina": {
              "url": "https://homebrew.bintray.com/bottles/jq-1.6.catalina.bottle.1.tar.gz",
              "sha256": "820a3c85fcbb63088b160c7edf125d7e55fc2c5c1d51569304499c9cc4b89ce8"
            },
            "mojave": {
              "url": "https://homebrew.bintray.com/bottles/jq-1.6.mojave.bottle.1.tar.gz",
              "sha256": "71f0e76c5b22e5088426c971d5e795fe67abee7af6c2c4ae0cf4c0eb98ed21ff"
            },
            "high_sierra": {
              "url": "https://homebrew.bintray.com/bottles/jq-1.6.high_sierra.bottle.1.tar.gz",
              "sha256": "dffcffa4ea13e8f0f2b45c5121e529077e135ae9a47254c32182231662ee9b72"
            },
            "sierra": {
              "url": "https://homebrew.bintray.com/bottles/jq-1.6.sierra.bottle.1.tar.gz",
              "sha256": "bb4d19dc026c2d72c53eed78eaa0ab982e9fcad2cd2acc6d13e7a12ff658e877"
            }
          }
        }
      },
      "tree": {
        "version": "1.8.0",
        "bottle": {
          "cellar": ":any_skip_relocation",
          "prefix": "/usr/local",
          "files": {
            "catalina": {
              "url": "https://homebrew.bintray.com/bottles/tree-1.8.0.catalina.bottle.tar.gz",
              "sha256": "18f7984bdbab22251e9fc3c7832dbace5c7f7a77e8d63717bb0078385e2bf255"
            },
            "mojave": {
              "url": "https://homebrew.bintray.com/bottles/tree-1.8.0.mojave.bottle.tar.gz",
              "sha256": "7152288c457dd893de50fa9d6ac9a8599748564e1b3586eec8eff7057089051a"
            },
            "high_sierra": {
              "url": "https://homebrew.bintray.com/bottles/tree-1.8.0.high_sierra.bottle.tar.gz",
              "sha256": "107d965994381d34e90b58a62f1c306c1b8a698db2696cdd905ba65c801ecc3b"
            },
            "sierra": {
              "url": "https://homebrew.bintray.com/bottles/tree-1.8.0.sierra.bottle.tar.gz",
              "sha256": "07d980571469a0cc699c69a8726eee338f782ba61c041e58f01ddb2924d08aeb"
            }
          }
        }
      },
      "hub": {
        "version": "2.14.2",
        "bottle": {
          "cellar": ":any_skip_relocation",
          "prefix": "/usr/local",
          "files": {
            "catalina": {
              "url": "https://homebrew.bintray.com/bottles/hub-2.14.2.catalina.bottle.tar.gz",
              "sha256": "fdf05855839a9d7ec6e7bee6796e3cb5fc473500cffc002366cf98c09a805b69"
            },
            "mojave": {
              "url": "https://homebrew.bintray.com/bottles/hub-2.14.2.mojave.bottle.tar.gz",
              "sha256": "bcbae9c683d76f3395665467ba0f0c00c60c12c84022f72faba4b8981724b563"
            },
            "high_sierra": {
              "url": "https://homebrew.bintray.com/bottles/hub-2.14.2.high_sierra.bottle.tar.gz",
              "sha256": "8800cda4532784bf764ea6116a06c81d8d90bb3d36d8ecf295e64f9dd647c4ad"
            }
          }
        }
      },
      "dep": {
        "version": "0.5.4",
        "bottle": {
          "cellar": ":any_skip_relocation",
          "prefix": "/usr/local",
          "files": {
            "catalina": {
              "url": "https://homebrew.bintray.com/bottles/dep-0.5.4.catalina.bottle.tar.gz",
              "sha256": "326ba98bcef16dc8823dd9fe76657e6ff0088a0669c0f857a05dd51867220bb7"
            },
            "mojave": {
              "url": "https://homebrew.bintray.com/bottles/dep-0.5.4.mojave.bottle.tar.gz",
              "sha256": "33200b5422fac00416ac44c7c28ad5aa627b845cd4d9aeb7002f7d41304deab0"
            },
            "high_sierra": {
              "url": "https://homebrew.bintray.com/bottles/dep-0.5.4.high_sierra.bottle.tar.gz",
              "sha256": "29cfe5b8c29bfbb09a93087dfbd30a9894ed596d3a4219072f022a001d2975cd"
            },
            "sierra": {
              "url": "https://homebrew.bintray.com/bottles/dep-0.5.4.sierra.bottle.tar.gz",
              "sha256": "ef9a0a978cbf2d4e537d21c4ff7b89a75b66228697b0aa348daa2284bc7362a9"
            }
          }
        }
      },
      "node": {
        "version": "13.12.0",
        "bottle": {
          "cellar": ":any",
          "prefix": "/usr/local",
          "files": {
            "catalina": {
              "url": "https://homebrew.bintray.com/bottles/node-13.12.0.catalina.bottle.tar.gz",
              "sha256": "fc0bfb42fe23e960e4a3e361cd1a4361a3560fce8b8903e409b78ed3ff4b6f18"
            },
            "mojave": {
              "url": "https://homebrew.bintray.com/bottles/node-13.12.0.mojave.bottle.tar.gz",
              "sha256": "3c7bd9a033032ab3d5d45e09382e6b36c37219a32194809248e9e2a05eb6f06e"
            },
            "high_sierra": {
              "url": "https://homebrew.bintray.com/bottles/node-13.12.0.high_sierra.bottle.tar.gz",
              "sha256": "e3de90c12bb492f857e5a0206ccedd4ae9137c9b1d2e5f5bdae6ff84f3b5bf0f"
            }
          }
        }
      },
      "sqlite3": null,
      "pandoc": {
        "version": "2.9.2.1",
        "bottle": {
          "cellar": ":any_skip_relocation",
          "prefix": "/usr/local",
          "files": {
            "catalina": {
              "url": "https://homebrew.bintray.com/bottles/pandoc-2.9.2.1.catalina.bottle.tar.gz",
              "sha256": "040eafbe1ebb8fe4c2b27425d7d3e566770c8c531eee7fdec2c96e01f4bf32a4"
            },
            "mojave": {
              "url": "https://homebrew.bintray.com/bottles/pandoc-2.9.2.1.mojave.bottle.tar.gz",
              "sha256": "61493929e5168952bc5bc64149bf67f8bec818313950aee764273b146b126442"
            },
            "high_sierra": {
              "url": "https://homebrew.bintray.com/bottles/pandoc-2.9.2.1.high_sierra.bottle.tar.gz",
              "sha256": "0fa6bfa3d880c8dcc41a469bd60ae74202094fb16bf6ca7ed48bf1cba11aea0b"
            }
          }
        }
      },
      "redis": {
        "version": "5.0.8",
        "bottle": {
          "cellar": ":any_skip_relocation",
          "prefix": "/usr/local",
          "files": {
            "catalina": {
              "url": "https://homebrew.bintray.com/bottles/redis-5.0.8.catalina.bottle.tar.gz",
              "sha256": "6dd79cce0a271a736f17a9c0e72fd8e5288b135426f5746d25496ab5048e0059"
            },
            "mojave": {
              "url": "https://homebrew.bintray.com/bottles/redis-5.0.8.mojave.bottle.tar.gz",
              "sha256": "c72def1c78f6c24c02d47de80a0b5ae5ef67640a42a38d040c503429eb02d3b1"
            },
            "high_sierra": {
              "url": "https://homebrew.bintray.com/bottles/redis-5.0.8.high_sierra.bottle.tar.gz",
              "sha256": "819c9292b32c8bdc90f51a7301cb44ffba8fa97fa8cf0db0e64e6ab5b0e41b9f"
            }
          }
        }
      },
      "nginx": {
        "version": "1.17.9",
        "bottle": {
          "cellar": "/usr/local/Cellar",
          "prefix": "/usr/local",
          "files": {
            "catalina": {
              "url": "https://homebrew.bintray.com/bottles/nginx-1.17.9.catalina.bottle.tar.gz",
              "sha256": "bbfea4efeecb097256a93ccedfe592ed6fc3a3d8d7cb348ea8ef0dc11052c866"
            },
            "mojave": {
              "url": "https://homebrew.bintray.com/bottles/nginx-1.17.9.mojave.bottle.tar.gz",
              "sha256": "d96a65f612fba7bd7982fadb2469b965dfc9d406c948c9a15c6407d22b64f510"
            },
            "high_sierra": {
              "url": "https://homebrew.bintray.com/bottles/nginx-1.17.9.high_sierra.bottle.tar.gz",
              "sha256": "865acfbcf15641757a278127cb3a70ed500f3220b4708e10ecafc4f87192016a"
            }
          }
        }
      },
      "gnupg": {
        "version": "2.2.20",
        "bottle": {
          "cellar": "/usr/local/Cellar",
          "prefix": "/usr/local",
          "files": {
            "catalina": {
              "url": "https://homebrew.bintray.com/bottles/gnupg-2.2.20.catalina.bottle.tar.gz",
              "sha256": "527ac31afe998a9931a6648c6fcc7288462ae73d6e6e8b84ecf46561c82d50ec"
            },
            "mojave": {
              "url": "https://homebrew.bintray.com/bottles/gnupg-2.2.20.mojave.bottle.tar.gz",
              "sha256": "e826cf4b1764da749eba007097be8077f433e52d8f96405044e57a384b114942"
            },
            "high_sierra": {
              "url": "https://homebrew.bintray.com/bottles/gnupg-2.2.20.high_sierra.bottle.tar.gz",
              "sha256": "179b68a29fe9f6731a294a674fbd439623acf22c1997c68b6358808adc83b763"
            }
          }
        }
      },
      "golang-migrate": {
        "version": "4.10.0",
        "bottle": {
          "cellar": ":any_skip_relocation",
          "prefix": "/usr/local",
          "files": {
            "catalina": {
              "url": "https://homebrew.bintray.com/bottles/golang-migrate-4.10.0.catalina.bottle.tar.gz",
              "sha256": "7c123be8ebd6c27ec7dd405ef4430d51a0200aebff16aa3a7b85ce2ebce4cd3c"
            },
            "mojave": {
              "url": "https://homebrew.bintray.com/bottles/golang-migrate-4.10.0.mojave.bottle.tar.gz",
              "sha256": "15a02a1b2534b3078ece9ef5197cd822688154ccc74288fde0770ccebbd8608f"
            },
            "high_sierra": {
              "url": "https://homebrew.bintray.com/bottles/golang-migrate-4.10.0.high_sierra.bottle.tar.gz",
              "sha256": "d154952644c694027e3931fba144201db04fee996a59f32982b5dfddb37fa1ab"
            }
          }
        }
      },
      "awscli": {
        "version": "2.0.7",
        "bottle": {
          "cellar": "/usr/local/Cellar",
          "prefix": "/usr/local",
          "files": {
            "catalina": {
              "url": "https://homebrew.bintray.com/bottles/awscli-2.0.7.catalina.bottle.tar.gz",
              "sha256": "925885df0b2bb6e76c8a3d2ed0764c4f981392e3227c599f5e7a57a7618c5813"
            },
            "mojave": {
              "url": "https://homebrew.bintray.com/bottles/awscli-2.0.7.mojave.bottle.tar.gz",
              "sha256": "6683a1928200bc6e9d8e1211de913387770eb1df2f7cc030d15884d32595bca9"
            },
            "high_sierra": {
              "url": "https://homebrew.bintray.com/bottles/awscli-2.0.7.high_sierra.bottle.tar.gz",
              "sha256": "e58b5fd9ca92fa48040c9182c2dde293d4dcf5474b7d1164b46f7f3c171aec35"
            }
          }
        }
      },
      "pulumi": {
        "version": "1.14.0",
        "bottle": {
          "cellar": ":any_skip_relocation",
          "prefix": "/usr/local",
          "files": {
            "catalina": {
              "url": "https://homebrew.bintray.com/bottles/pulumi-1.14.0.catalina.bottle.tar.gz",
              "sha256": "f8a22bc2dd23579a32359926cb63db6dd4ee313683cc6d56234740da76fec465"
            },
            "mojave": {
              "url": "https://homebrew.bintray.com/bottles/pulumi-1.14.0.mojave.bottle.tar.gz",
              "sha256": "3ecaf0853980d7d53f43997d36da42020f8f28fdeac12c921c7a9cc52ab661db"
            },
            "high_sierra": {
              "url": "https://homebrew.bintray.com/bottles/pulumi-1.14.0.high_sierra.bottle.tar.gz",
              "sha256": "4c93c36683f2fe1daedc37fe41ab93cf19fd42e1c4edb32159a277dc84601073"
            }
          }
        }
      },
      "hugo": {
        "version": "0.68.3",
        "bottle": {
          "cellar": ":any_skip_relocation",
          "prefix": "/usr/local",
          "files": {
            "catalina": {
              "url": "https://homebrew.bintray.com/bottles/hugo-0.68.3.catalina.bottle.tar.gz",
              "sha256": "202cb22f91d546939c3e7d11a360b39eb67e445b41f8a8114c35c6cb26d7a7d1"
            },
            "mojave": {
              "url": "https://homebrew.bintray.com/bottles/hugo-0.68.3.mojave.bottle.tar.gz",
              "sha256": "9b93809ed925204a4d34458044e5d81e152c43c10debaf87509007f45b84bec3"
            },
            "high_sierra": {
              "url": "https://homebrew.bintray.com/bottles/hugo-0.68.3.high_sierra.bottle.tar.gz",
              "sha256": "71684aacddbb3d971ea53de453cc8de91c15501ef3db9fab5077a43aa6bd73ee"
            }
          }
        }
      },
      "proctools": {
        "version": "0.4pre1",
        "bottle": {
          "cellar": ":any_skip_relocation",
          "prefix": "/usr/local",
          "files": {
            "catalina": {
              "url": "https://homebrew.bintray.com/bottles/proctools-0.4pre1.catalina.bottle.tar.gz",
              "sha256": "f0fe70530d22c270ac3d5a105f2dbbbb0dc6a664acd03f3ad7da3f86255fd548"
            },
            "mojave": {
              "url": "https://homebrew.bintray.com/bottles/proctools-0.4pre1.mojave.bottle.tar.gz",
              "sha256": "f7466405a3aab3cd7b00669ea685b1fe463a19bbdd7fef8b8c25f86595de2d34"
            },
            "high_sierra": {
              "url": "https://homebrew.bintray.com/bottles/proctools-0.4pre1.high_sierra.bottle.tar.gz",
              "sha256": "d41f76776e37f54cabf5d76ce2cb89d13052f1221a70b325245f600a7bd047ae"
            },
            "sierra": {
              "url": "https://homebrew.bintray.com/bottles/proctools-0.4pre1.sierra.bottle.tar.gz",
              "sha256": "8567dd0ffde620f8b1dd18e0529d670a235bcde6dac7b3f19d6528ecf843613a"
            },
            "el_capitan": {
              "url": "https://homebrew.bintray.com/bottles/proctools-0.4pre1.el_capitan.bottle.tar.gz",
              "sha256": "ed8136da9f7b607eec69d014b1c3f81b9ef3f004f38cc2904400861c0d6adab0"
            },
            "yosemite": {
              "url": "https://homebrew.bintray.com/bottles/proctools-0.4pre1.yosemite.bottle.tar.gz",
              "sha256": "a05e2adbc0ff0e11be133a81748fc123adc8b32002ff5efb49d141a354f92d70"
            },
            "mavericks": {
              "url": "https://homebrew.bintray.com/bottles/proctools-0.4pre1.mavericks.bottle.tar.gz",
              "sha256": "812961a8a321441010a786c4de1b97c830181a013dae457b6b44c96ce799eb22"
            }
          }
        }
      },
      "watchman": {
        "version": "4.9.0_3",
        "bottle": {
          "cellar": "/usr/local/Cellar",
          "prefix": "/usr/local",
          "files": {
            "catalina": {
              "url": "https://homebrew.bintray.com/bottles/watchman-4.9.0_3.catalina.bottle.tar.gz",
              "sha256": "7c01f1d4e6e8c15ec4d3625520b7e43e245d22f33ce7319dc962b7cb0b9b3d5d"
            },
            "mojave": {
              "url": "https://homebrew.bintray.com/bottles/watchman-4.9.0_3.mojave.bottle.tar.gz",
              "sha256": "a9b3039561abdde021ba080ee1e37984f7f56184476a4ffee1db476561f92d83"
            },
            "high_sierra": {
              "url": "https://homebrew.bintray.com/bottles/watchman-4.9.0_3.high_sierra.bottle.tar.gz",
              "sha256": "158a3dcce76f01446c9264a6f623a1c6be339118760ce61d88a9d38e2676ad45"
            },
            "sierra": {
              "url": "https://homebrew.bintray.com/bottles/watchman-4.9.0_3.sierra.bottle.tar.gz",
              "sha256": "013faefc9001613c58680e5626b36fe943ca943649882054fbfbefccf4796415"
            }
          }
        }
      },
      "tldr": {
        "version": "1.3.0_2",
        "bottle": {
          "cellar": ":any",
          "prefix": "/usr/local",
          "files": {
            "catalina": {
              "url": "https://homebrew.bintray.com/bottles/tldr-1.3.0_2.catalina.bottle.tar.gz",
              "sha256": "bf2ea4c6b18e4fe9e7a49962273839446bb453f6b7d097abdb0149f5d1383cc0"
            },
            "mojave": {
              "url": "https://homebrew.bintray.com/bottles/tldr-1.3.0_2.mojave.bottle.tar.gz",
              "sha256": "c5f99efa930b7f80647496c83fe118bd184feae7c5f256dc67d7594aceba7120"
            },
            "high_sierra": {
              "url": "https://homebrew.bintray.com/bottles/tldr-1.3.0_2.high_sierra.bottle.tar.gz",
              "sha256": "00f5ce204fa62e51ed3be821abba9fdda36335b6cecf65231158c02b9713f357"
            },
            "sierra": {
              "url": "https://homebrew.bintray.com/bottles/tldr-1.3.0_2.sierra.bottle.tar.gz",
              "sha256": "06f9609695fb6b14bbd78f3246bb176b341aecda6ce70515723cee8e8e4ced69"
            },
            "el_capitan": {
              "url": "https://homebrew.bintray.com/bottles/tldr-1.3.0_2.el_capitan.bottle.tar.gz",
              "sha256": "209c571e3472128665194e73451199087236758a0a7cfa6e88ffd7aa444abbac"
            }
          }
        }
      },
      "vegeta": {
        "version": "12.8.3",
        "bottle": {
          "cellar": ":any_skip_relocation",
          "prefix": "/usr/local",
          "files": {
            "catalina": {
              "url": "https://homebrew.bintray.com/bottles/vegeta-12.8.3.catalina.bottle.tar.gz",
              "sha256": "f93a70561ffc7d97fb58638e1555148058036f1b65ee3b0891352346a256c8d5"
            },
            "mojave": {
              "url": "https://homebrew.bintray.com/bottles/vegeta-12.8.3.mojave.bottle.tar.gz",
              "sha256": "f3496b02858387a32051d015677ca417c04251b2a98b6d36d8611836908dd23e"
            },
            "high_sierra": {
              "url": "https://homebrew.bintray.com/bottles/vegeta-12.8.3.high_sierra.bottle.tar.gz",
              "sha256": "d03417e5f8bf936b8fa726f6ec25607809db1e284a4ca98ebf884fea3825ec49"
            }
          }
        }
      },
      "graphviz": {
        "version": "2.42.3",
        "bottle": {
          "cellar": "/usr/local/Cellar",
          "prefix": "/usr/local",
          "files": {
            "catalina": {
              "url": "https://homebrew.bintray.com/bottles/graphviz-2.42.3.catalina.bottle.tar.gz",
              "sha256": "ad22bb28b684c6fb9c51e32000ada1df8cc2f6f2711f8e85c4599fbb5e213e7e"
            },
            "mojave": {
              "url": "https://homebrew.bintray.com/bottles/graphviz-2.42.3.mojave.bottle.tar.gz",
              "sha256": "7f11871b1618a4e005a38462522b251bda2c97701aaa944b77a82e212d928ba7"
            },
            "high_sierra": {
              "url": "https://homebrew.bintray.com/bottles/graphviz-2.42.3.high_sierra.bottle.tar.gz",
              "sha256": "9b7c8b58ae0ab87ab5af31f6d72c61e9840f3fbb24029156a937bb1d3d75310b"
            }
          }
        }
      },
      "gcc": {
        "version": "9.3.0",
        "bottle": {
          "cellar": "/usr/local/Cellar",
          "prefix": "/usr/local",
          "files": {
            "catalina": {
              "url": "https://homebrew.bintray.com/bottles/gcc-9.3.0.catalina.bottle.tar.gz",
              "sha256": "6b84b7dcd0fe04ca70e7cac5dcf35f8a256f5620ddb671a91e10b0bb692f587e"
            },
            "mojave": {
              "url": "https://homebrew.bintray.com/bottles/gcc-9.3.0.mojave.bottle.tar.gz",
              "sha256": "af7aa4f1aee84374500b1150fe6ce58c381e0f133b4f8cd674955b9d4d22efe8"
            },
            "high_sierra": {
              "url": "https://homebrew.bintray.com/bottles/gcc-9.3.0.high_sierra.bottle.tar.gz",
              "sha256": "75c2a1e504d82b82d0cbbab4be731004077794d4ed7f5f102123001a50909a48"
            }
          }
        }
      },
      "universal-ctags": {
        "version": "HEAD-8c6eab6",
        "bottle": false,
        "options": {
          "args": [
            "HEAD"
          ]
        }
      },
      "ruplacer": {
        "version": "0.4.1",
        "bottle": false
      },
      "asdf": {
        "version": "0.7.8",
        "bottle": false
      },
      "automake": {
        "version": "1.16.2",
        "bottle": {
          "cellar": ":any_skip_relocation",
          "prefix": "/usr/local",
          "files": {
            "catalina": {
              "url": "https://homebrew.bintray.com/bottles/automake-1.16.2.catalina.bottle.tar.gz",
              "sha256": "fe26d4df57481b6a7ca0a6915c37c53648c27ffb41926b3570c45f80fdd8888e"
            },
            "mojave": {
              "url": "https://homebrew.bintray.com/bottles/automake-1.16.2.mojave.bottle.tar.gz",
              "sha256": "fe26d4df57481b6a7ca0a6915c37c53648c27ffb41926b3570c45f80fdd8888e"
            },
            "high_sierra": {
              "url": "https://homebrew.bintray.com/bottles/automake-1.16.2.high_sierra.bottle.tar.gz",
              "sha256": "fe26d4df57481b6a7ca0a6915c37c53648c27ffb41926b3570c45f80fdd8888e"
            }
          }
        }
      },
      "autoconf": {
        "version": "2.69",
        "bottle": {
          "cellar": ":any_skip_relocation",
          "prefix": "/usr/local",
          "files": {
            "catalina": {
              "url": "https://homebrew.bintray.com/bottles/autoconf-2.69.catalina.bottle.4.tar.gz",
              "sha256": "ca510b350e941fb9395522a03f9d2fb5df276085d806ceead763acb95889a368"
            },
            "mojave": {
              "url": "https://homebrew.bintray.com/bottles/autoconf-2.69.mojave.bottle.4.tar.gz",
              "sha256": "9724736d34773b6e41e2434ffa28fe79feccccf7b7786e54671441ca75115cdb"
            },
            "high_sierra": {
              "url": "https://homebrew.bintray.com/bottles/autoconf-2.69.high_sierra.bottle.4.tar.gz",
              "sha256": "63957a3952b7af5496012b3819c9956822fd7d895d63339c23fdc65c502e1a40"
            },
            "sierra": {
              "url": "https://homebrew.bintray.com/bottles/autoconf-2.69.sierra.bottle.4.tar.gz",
              "sha256": "a76fca79a00f733c1c9f75600b906de4755dd3fbb595b1b55ded1347ac141607"
            },
            "el_capitan": {
              "url": "https://homebrew.bintray.com/bottles/autoconf-2.69.el_capitan.bottle.4.tar.gz",
              "sha256": "ded69c7dac4bc8747e52dca37d6d561e55e3162649d3805572db0dc2f940a4b8"
            },
            "yosemite": {
              "url": "https://homebrew.bintray.com/bottles/autoconf-2.69.yosemite.bottle.4.tar.gz",
              "sha256": "daf70656aa9ff8b2fb612324222aa6b5e900e2705c9f555198bcd8cd798d7dd0"
            },
            "mavericks": {
              "url": "https://homebrew.bintray.com/bottles/autoconf-2.69.mavericks.bottle.4.tar.gz",
              "sha256": "d153b3318754731ff5e91b45b2518c75880993fa9d1f312a03696e2c1de0c9d5"
            }
          }
        }
      },
      "libyaml": {
        "version": "0.2.2",
        "bottle": {
          "cellar": ":any",
          "prefix": "/usr/local",
          "files": {
            "catalina": {
              "url": "https://homebrew.bintray.com/bottles/libyaml-0.2.2.catalina.bottle.tar.gz",
              "sha256": "63cf355fb4b9fb7e33cb9d0b9b366252f680d887cb5d7e12de8468381aa5f000"
            },
            "mojave": {
              "url": "https://homebrew.bintray.com/bottles/libyaml-0.2.2.mojave.bottle.tar.gz",
              "sha256": "aa23980d03fe5bd2e60d59424061b7ac91c24f315de84ec33856ab3bf44de0af"
            },
            "high_sierra": {
              "url": "https://homebrew.bintray.com/bottles/libyaml-0.2.2.high_sierra.bottle.tar.gz",
              "sha256": "b763aa33bfdf6dca21b3bc16919217939ec28916266bb476ff8f44e777bde176"
            },
            "sierra": {
              "url": "https://homebrew.bintray.com/bottles/libyaml-0.2.2.sierra.bottle.tar.gz",
              "sha256": "35d27c9b0709f142d5d30a2d37566d85dafcd023f64016d042282eeaf94102b7"
            }
          }
        }
      },
      "readline": {
        "version": "8.0.4",
        "bottle": {
          "cellar": ":any",
          "prefix": "/usr/local",
          "files": {
            "catalina": {
              "url": "https://homebrew.bintray.com/bottles/readline-8.0.4.catalina.bottle.tar.gz",
              "sha256": "6ae1c8e7c783f32bd22c6085caa4d838fed7fb386da7e40ca47b87ec9b1237d6"
            },
            "mojave": {
              "url": "https://homebrew.bintray.com/bottles/readline-8.0.4.mojave.bottle.tar.gz",
              "sha256": "29f7102a730ab39c8312cad1e7e439f6da2a67c452ce2b3380581eb185a5d8e8"
            },
            "high_sierra": {
              "url": "https://homebrew.bintray.com/bottles/readline-8.0.4.high_sierra.bottle.tar.gz",
              "sha256": "896a3d50ce8962ba56e853bdd590fadeabc00ab36475d143d6c2bea5cc15bb28"
            }
          }
        }
      },
      "libxslt": {
        "version": "1.1.34",
        "bottle": {
          "cellar": ":any",
          "prefix": "/usr/local",
          "files": {
            "catalina": {
              "url": "https://homebrew.bintray.com/bottles/libxslt-1.1.34.catalina.bottle.tar.gz",
              "sha256": "cbadecf3186f45754220dff4cbdfbb576882a211d615b52249a4c9d8ba4d7c3a"
            },
            "mojave": {
              "url": "https://homebrew.bintray.com/bottles/libxslt-1.1.34.mojave.bottle.tar.gz",
              "sha256": "6feb1b8d57dd0d8b651733720d4dac728d2e27cf8c9fa9f88e60612fe0a0c882"
            },
            "high_sierra": {
              "url": "https://homebrew.bintray.com/bottles/libxslt-1.1.34.high_sierra.bottle.tar.gz",
              "sha256": "733c15b756070866d08196dcd5eef9facea1ce98d9c233cd6bf73fa426e0d062"
            }
          }
        }
      },
      "libtool": {
        "version": "2.4.6_1",
        "bottle": {
          "cellar": ":any",
          "prefix": "/usr/local",
          "files": {
            "catalina": {
              "url": "https://homebrew.bintray.com/bottles/libtool-2.4.6_1.catalina.bottle.tar.gz",
              "sha256": "38212486e78db33048438cffe38b6914f13553e7bb8c7d3d2fbecb18a6481d3c"
            },
            "mojave": {
              "url": "https://homebrew.bintray.com/bottles/libtool-2.4.6_1.mojave.bottle.tar.gz",
              "sha256": "c92ab35c3706c255a36b733aa7a475159da9cf375c275d230fd6a7802a94e4dc"
            },
            "high_sierra": {
              "url": "https://homebrew.bintray.com/bottles/libtool-2.4.6_1.high_sierra.bottle.tar.gz",
              "sha256": "ebb50367eb2336ee317841587e24690de124fb2c3e4d346405e9b41c4e6120ae"
            },
            "sierra": {
              "url": "https://homebrew.bintray.com/bottles/libtool-2.4.6_1.sierra.bottle.tar.gz",
              "sha256": "78a1f6c6644eae01eb5c204ef705f7e48721a0fe8ece492c10c84791061885db"
            },
            "el_capitan": {
              "url": "https://homebrew.bintray.com/bottles/libtool-2.4.6_1.el_capitan.bottle.tar.gz",
              "sha256": "b7651d0a082e2f103f03ca3a5ed831e2ff5655ccc1044ac0452e4d1825475a35"
            },
            "yosemite": {
              "url": "https://homebrew.bintray.com/bottles/libtool-2.4.6_1.yosemite.bottle.tar.gz",
              "sha256": "0eb206c0f51e8ce2e3e9340b5ce3c8ecef961ae6696f676073327a7ac04e5c0b"
            },
            "mavericks": {
              "url": "https://homebrew.bintray.com/bottles/libtool-2.4.6_1.mavericks.bottle.tar.gz",
              "sha256": "2e51ef82ef2bd1ad9d921a9016b9e5d7fa82d131849e2c32a3c90daa119e2eda"
            }
          }
        }
      },
      "unixodbc": {
        "version": "2.3.7",
        "bottle": {
          "cellar": "/usr/local/Cellar",
          "prefix": "/usr/local",
          "files": {
            "catalina": {
              "url": "https://homebrew.bintray.com/bottles/unixodbc-2.3.7.catalina.bottle.1.tar.gz",
              "sha256": "03ba378d971af98d07652f978548ffacb4c155ba11dd36af9d46af36e2d5674b"
            },
            "mojave": {
              "url": "https://homebrew.bintray.com/bottles/unixodbc-2.3.7.mojave.bottle.1.tar.gz",
              "sha256": "d9f30688c0639d73b9e3a4b4b94d3679b2762e2cf0bff6b2ad64fcd175cc30ca"
            },
            "high_sierra": {
              "url": "https://homebrew.bintray.com/bottles/unixodbc-2.3.7.high_sierra.bottle.1.tar.gz",
              "sha256": "0b30b166c0e6bbd9df375a018d0f2a80b944617230b15531093d20eb015971e6"
            },
            "sierra": {
              "url": "https://homebrew.bintray.com/bottles/unixodbc-2.3.7.sierra.bottle.1.tar.gz",
              "sha256": "44407c41dc2c5cc58fcd2c254fa54ede75e7782b82567f4f1ba421d357203105"
            }
          }
        }
      },
      "unzip": {
        "version": "6.0_6",
        "bottle": {
          "cellar": ":any_skip_relocation",
          "prefix": "/usr/local",
          "files": {
            "catalina": {
              "url": "https://homebrew.bintray.com/bottles/unzip-6.0_6.catalina.bottle.tar.gz",
              "sha256": "178cea56554b0e6b74856203340554c7615c6ed2e122059c78370e35c896f0ce"
            },
            "mojave": {
              "url": "https://homebrew.bintray.com/bottles/unzip-6.0_6.mojave.bottle.tar.gz",
              "sha256": "f0b95f2d5c664f45686f3aa318384906014ed28939da28020d12138f025aaeb6"
            },
            "high_sierra": {
              "url": "https://homebrew.bintray.com/bottles/unzip-6.0_6.high_sierra.bottle.tar.gz",
              "sha256": "6dd7d0862f5a8b954dd94b3c91378209e0086eec7c5be367af0d8c330bc099da"
            },
            "sierra": {
              "url": "https://homebrew.bintray.com/bottles/unzip-6.0_6.sierra.bottle.tar.gz",
              "sha256": "f4d59c04a44f93a30a23ec403784c73f9c06db9b72f3277679f66b1870a94331"
            }
          }
        }
      },
      "opam": {
        "version": "2.0.6",
        "bottle": {
          "cellar": ":any_skip_relocation",
          "prefix": "/usr/local",
          "files": {
            "catalina": {
              "url": "https://homebrew.bintray.com/bottles/opam-2.0.6.catalina.bottle.tar.gz",
              "sha256": "54e18e947ab5a8d2af76cefeb3707be24ad54d4d475851b372aac766d5350d14"
            },
            "mojave": {
              "url": "https://homebrew.bintray.com/bottles/opam-2.0.6.mojave.bottle.tar.gz",
              "sha256": "6c2a6796eead34e1116bd37e0ade8a1ad34ceeef98e396cfc36f26d591a21de6"
            },
            "high_sierra": {
              "url": "https://homebrew.bintray.com/bottles/opam-2.0.6.high_sierra.bottle.tar.gz",
              "sha256": "941366068ed9c5743d09635128defeecfcf52b3663a1fbff04d2003ded76ae89"
            }
          }
        }
      },
      "pkg-config": {
        "version": "0.29.2_2",
        "bottle": {
          "cellar": ":any_skip_relocation",
          "prefix": "/usr/local",
          "files": {
            "catalina": {
              "url": "https://homebrew.bintray.com/bottles/pkg-config-0.29.2_2.catalina.bottle.tar.gz",
              "sha256": "4a2e91af708c59447cced59a5f2df26570c9534dc89333acf7e3d965858c5718"
            },
            "mojave": {
              "url": "https://homebrew.bintray.com/bottles/pkg-config-0.29.2_2.mojave.bottle.tar.gz",
              "sha256": "f284f811f88f8741b88d7bf607fd6d7791fcfa6559802c81f687bb5852376241"
            },
            "high_sierra": {
              "url": "https://homebrew.bintray.com/bottles/pkg-config-0.29.2_2.high_sierra.bottle.tar.gz",
              "sha256": "b41d6ea88bfcacc5ce62bdf2ba97028ecc6864043875cfde9669125ba2af7d13"
            }
          }
        }
      },
      "pcre": {
        "version": "8.44",
        "bottle": {
          "cellar": ":any",
          "prefix": "/usr/local",
          "files": {
            "catalina": {
              "url": "https://homebrew.bintray.com/bottles/pcre-8.44.catalina.bottle.tar.gz",
              "sha256": "f8ac266e04f984fa55091a43f0fdc39a40d57c2489d289a186c88ccedaba7eeb"
            },
            "mojave": {
              "url": "https://homebrew.bintray.com/bottles/pcre-8.44.mojave.bottle.tar.gz",
              "sha256": "ed9b483538da7bc6559d2e63dd36659736fab9510681661d970d707a18731de4"
            },
            "high_sierra": {
              "url": "https://homebrew.bintray.com/bottles/pcre-8.44.high_sierra.bottle.tar.gz",
              "sha256": "aeea1351e1439847d00c3cee54bd28639493e686f809568cf42fea7bb28da2a5"
            }
          }
        }
      },
      "chezscheme": {
        "version": "9.5.2",
        "bottle": {
          "cellar": ":any_skip_relocation",
          "prefix": "/usr/local",
          "files": {
            "catalina": {
              "url": "https://homebrew.bintray.com/bottles/chezscheme-9.5.2.catalina.bottle.tar.gz",
              "sha256": "bdb3d3f12a298ea57126c21264fefbec72d45b15cd6274d458c401ab96a2abd3"
            },
            "mojave": {
              "url": "https://homebrew.bintray.com/bottles/chezscheme-9.5.2.mojave.bottle.tar.gz",
              "sha256": "22a69bfdc7cc44396429124104397dc5377b4e1b184064c8adec33bd0ff6203d"
            },
            "high_sierra": {
              "url": "https://homebrew.bintray.com/bottles/chezscheme-9.5.2.high_sierra.bottle.tar.gz",
              "sha256": "3ce7b28cde766fe8b6f4c517182b5c21f38371108839712ac85c94f3fcd4a07a"
            },
            "sierra": {
              "url": "https://homebrew.bintray.com/bottles/chezscheme-9.5.2.sierra.bottle.tar.gz",
              "sha256": "e26d93d7b1c4bfefa3238809c81cfe6b30a3d0fd57e716bb712a1258cb05d5f9"
            }
          }
        }
      },
      "exa": {
        "version": "0.9.0",
        "bottle": {
          "cellar": ":any_skip_relocation",
          "prefix": "/usr/local",
          "files": {
            "catalina": {
              "url": "https://homebrew.bintray.com/bottles/exa-0.9.0.catalina.bottle.tar.gz",
              "sha256": "cc484e7deb12cdae4ede810258be0ca069d7db395897e9d3fbadd501fb075743"
            },
            "mojave": {
              "url": "https://homebrew.bintray.com/bottles/exa-0.9.0.mojave.bottle.tar.gz",
              "sha256": "bc80009ad845d914c08e6de1c39c97e0f4f180ef4f077b3ef1957cab519d6743"
            },
            "high_sierra": {
              "url": "https://homebrew.bintray.com/bottles/exa-0.9.0.high_sierra.bottle.tar.gz",
              "sha256": "7382b758899c756f94c4c99440f71075945d333e302e53139e423fb1798c852e"
            },
            "sierra": {
              "url": "https://homebrew.bintray.com/bottles/exa-0.9.0.sierra.bottle.tar.gz",
              "sha256": "9499359da5f5fffbd8b22c8cb8e78f0fdf99594c4d2b06e7ba58eb21afbcb582"
            }
          }
        }
      },
      "bat": {
        "version": "0.13.0",
        "bottle": {
          "cellar": ":any_skip_relocation",
          "prefix": "/usr/local",
          "files": {
            "catalina": {
              "url": "https://homebrew.bintray.com/bottles/bat-0.13.0.catalina.bottle.tar.gz",
              "sha256": "7a3940396b74afc976f97c19194dbbdcbe93268f6eb657fd4b3422ce60f03e8f"
            },
            "mojave": {
              "url": "https://homebrew.bintray.com/bottles/bat-0.13.0.mojave.bottle.tar.gz",
              "sha256": "67a235ef3a22a87d17333d44f547146b2d0c13fc1ec9b076133770b565176f51"
            },
            "high_sierra": {
              "url": "https://homebrew.bintray.com/bottles/bat-0.13.0.high_sierra.bottle.tar.gz",
              "sha256": "1dc30e4059defc1475a2969236fc058a218561d930ef3d7253f53f271d0f4c40"
            }
          }
        }
      },
      "moreutils": {
        "version": "0.63",
        "bottle": {
          "cellar": ":any_skip_relocation",
          "prefix": "/usr/local",
          "files": {
            "catalina": {
              "url": "https://homebrew.bintray.com/bottles/moreutils-0.63.catalina.bottle.tar.gz",
              "sha256": "0277b44f53cc7e581c338a28fa330e4d436cd05757d99cfc9baa1f5ca095af4c"
            },
            "mojave": {
              "url": "https://homebrew.bintray.com/bottles/moreutils-0.63.mojave.bottle.tar.gz",
              "sha256": "a3d5a342bf079998b52d172f0f5e8b066b256145e2eb3ded393a0e6e2680b573"
            },
            "high_sierra": {
              "url": "https://homebrew.bintray.com/bottles/moreutils-0.63.high_sierra.bottle.tar.gz",
              "sha256": "3731c1304a72a7a0486891bf592cd82b7422d0c37cadeb00b6f633e62f20aa35"
            },
            "sierra": {
              "url": "https://homebrew.bintray.com/bottles/moreutils-0.63.sierra.bottle.tar.gz",
              "sha256": "fac2ba67a62889ff07edb8257e0d13aa96143a7421521ffdf3e0cf685a1cdc1e"
            }
          }
        }
      },
      "kubernetes-cli": {
        "version": "1.18.0",
        "bottle": {
          "cellar": ":any_skip_relocation",
          "prefix": "/usr/local",
          "files": {
            "catalina": {
              "url": "https://homebrew.bintray.com/bottles/kubernetes-cli-1.18.0.catalina.bottle.tar.gz",
              "sha256": "061548196115c50d1e4b0923d1c5401adb62626feb59a0ed81aa6517477219ec"
            },
            "mojave": {
              "url": "https://homebrew.bintray.com/bottles/kubernetes-cli-1.18.0.mojave.bottle.tar.gz",
              "sha256": "0c47011e194e620777708ed29f243199aa9aa59b00f11ad70b21da6c2bc7db1e"
            },
            "high_sierra": {
              "url": "https://homebrew.bintray.com/bottles/kubernetes-cli-1.18.0.high_sierra.bottle.tar.gz",
              "sha256": "23e85356412bed6d80af7b27c8c5a7db9427d8983d30cfc9d48a7d9595a40fae"
            }
          }
        }
      },
      "kubectx": {
        "version": "0.8.0",
        "bottle": false
      },
      "watch": {
        "version": "3.3.16",
        "bottle": {
          "cellar": ":any",
          "prefix": "/usr/local",
          "files": {
            "catalina": {
              "url": "https://homebrew.bintray.com/bottles/watch-3.3.16.catalina.bottle.tar.gz",
              "sha256": "011e48363fe62c7a4ba0dec746d5964ee25545bde7855a31db0cb411420df190"
            },
            "mojave": {
              "url": "https://homebrew.bintray.com/bottles/watch-3.3.16.mojave.bottle.tar.gz",
              "sha256": "d17aba6f80c530e6b91b30e088df60aab3dc84b2f57ca7499928322438b9f0d2"
            },
            "high_sierra": {
              "url": "https://homebrew.bintray.com/bottles/watch-3.3.16.high_sierra.bottle.tar.gz",
              "sha256": "13d63ebc419965182d98f10b25cc99961679e1ba5ce6118e66b7037eb4e78de8"
            }
          }
        }
      },
      "yarn": {
        "version": "1.22.4",
        "bottle": false
      },
      "dust": {
        "version": "0.5.1",
        "bottle": {
          "cellar": ":any_skip_relocation",
          "prefix": "/usr/local",
          "files": {
            "catalina": {
              "url": "https://homebrew.bintray.com/bottles/dust-0.5.1.catalina.bottle.tar.gz",
              "sha256": "2d26a2fa524049d8b2a32b3076f7de243c7929c943b5c0190d8cc5c9a2ba41d3"
            },
            "mojave": {
              "url": "https://homebrew.bintray.com/bottles/dust-0.5.1.mojave.bottle.tar.gz",
              "sha256": "3e92fcb18d37bd8dde1d8e52a44c8f96a5086a7afb5ced6895262af0b3e8395b"
            },
            "high_sierra": {
              "url": "https://homebrew.bintray.com/bottles/dust-0.5.1.high_sierra.bottle.tar.gz",
              "sha256": "ffa147a323f5ff57cbea0eb8817acdfff88c1f349f5f1f35d0bf3dc64e6c8faf"
            }
          }
        }
      }
    },
    "cask": {
      "firefox": {
        "version": "66.0.3",
        "options": {
          "full_name": "firefox",
          "args": {
            "appdir": "/Applications"
          }
        }
      },
      "iterm2": {
        "version": "3.2.9",
        "options": {
          "full_name": "iterm2",
          "args": {
            "appdir": "/Applications"
          }
        }
      },
      "alfred": {
        "version": "4.0.3_1092",
        "options": {
          "full_name": "alfred",
          "args": {
            "appdir": "/Applications"
          }
        }
      },
      "1password": {
        "version": "7.2.5",
        "options": {
          "full_name": "1password",
          "args": {
            "appdir": "/Applications"
          }
        }
      },
      "dropbox": {
        "version": "latest",
        "options": {
          "full_name": "dropbox",
          "args": {
            "appdir": "/Applications"
          }
        }
      },
      "keepingyouawake": {
        "version": "1.5.0",
        "options": {
          "full_name": "keepingyouawake",
          "args": {
            "appdir": "/Applications"
          }
        }
      },
      "sizeup": {
        "version": "1.7.4",
        "options": {
          "full_name": "sizeup",
          "args": {
            "appdir": "/Applications"
          }
        }
      },
      "slack": {
        "version": "3.4.0",
        "options": {
          "full_name": "slack",
          "args": {
            "appdir": "/Applications"
          }
        }
      },
      "arq": {
        "version": "5.16",
        "options": {
          "full_name": "arq",
          "args": {
            "appdir": "/Applications"
          }
        }
      },
      "tunnelblick": {
        "version": "3.7.8,5180",
        "options": {
          "full_name": "tunnelblick",
          "args": {
            "appdir": "/Applications"
          }
        }
      },
      "istat-menus": {
        "version": "6.31",
        "options": {
          "full_name": "istat-menus",
          "args": {
            "appdir": "/Applications"
          }
        }
      },
      "zoomus": {
        "version": "4.4.52586.0416",
        "options": {
          "full_name": "zoomus",
          "args": {
            "appdir": "/Applications"
          }
        }
      },
      "racket": {
        "version": "7.6",
        "options": {
          "full_name": "racket",
          "args": {
            "appdir": "/Applications"
          }
        }
      },
      "docker": {
        "version": "2.0.0.3-ce-mac81,31259",
        "options": {
          "full_name": "docker",
          "args": {
            "appdir": "/Applications"
          }
        }
      },
      "whatsapp": {
        "version": "0.3.2848",
        "options": {
          "full_name": "whatsapp",
          "args": {
            "appdir": "/Applications"
          }
        }
      },
      "spotify": {
        "version": "latest",
        "options": {
          "full_name": "spotify",
          "args": {
            "appdir": "/Applications"
          }
        }
      },
      "karabiner-elements": {
        "version": "12.2.0",
        "options": {
          "full_name": "karabiner-elements",
          "args": {
            "appdir": "/Applications"
          }
        }
      },
      "vlc": {
        "version": "3.0.6",
        "options": {
          "full_name": "vlc",
          "args": {
            "appdir": "/Applications"
          }
        }
      },
      "adobe-acrobat-reader": {
        "version": "19.010.20099",
        "options": {
          "full_name": "adobe-acrobat-reader",
          "args": {
            "appdir": "/Applications"
          }
        }
      },
      "kitty": {
        "version": "0.17.2",
        "options": {
          "full_name": "kitty",
          "args": {
            "appdir": "/Applications"
          }
        }
      },
      "alacritty": {
        "version": "0.4.2",
        "options": {
          "full_name": "alacritty",
          "args": {
            "appdir": "/Applications"
          }
        }
      },
      "google-chrome": {
        "version": "74.0.3729.108",
        "options": {
          "full_name": "google-chrome",
          "args": {
            "appdir": "/Applications"
          }
        }
      },
      "virtualbox": {
        "version": "6.1.4,136177",
        "options": {
          "full_name": "virtualbox",
          "args": {
            "appdir": "/Applications"
          }
        }
      },
      "vagrant": {
        "version": "2.2.7",
        "options": {
          "full_name": "vagrant",
          "args": {
            "appdir": "/Applications"
          }
        }
      },
      "skype": {
        "version": "8.43.0.56",
        "options": {
          "full_name": "skype",
          "args": {
            "appdir": "/Applications"
          }
        }
      },
      "typora": {
        "version": "0.9.9.24.2",
        "options": {
          "full_name": "typora",
          "args": {
            "appdir": "/Applications"
          }
        }
      },
      "licecap": {
        "version": "1.30",
        "options": {
          "full_name": "licecap",
          "args": {
            "appdir": "/Applications"
          }
        }
      },
      "postgres": {
        "version": "2.2.2",
        "options": {
          "full_name": "postgres",
          "args": {
            "appdir": "/Applications"
          }
        }
      },
      "libreoffice": {
        "version": "6.4.2",
        "options": {
          "full_name": "libreoffice",
          "args": {
            "appdir": "/Applications"
          }
        }
      },
      "google-cloud-sdk": {
        "version": "latest",
        "options": {
          "full_name": "google-cloud-sdk",
          "args": {
            "appdir": "/Applications"
          }
        }
      },
      "visual-studio-code": {
        "version": "1.33.1,51b0b28134d51361cf996d2f0a1c698247aeabd8",
        "options": {
          "full_name": "visual-studio-code",
          "args": {
            "appdir": "/Applications"
          }
        }
      },
      "pgadmin4": {
        "version": "4.20",
        "options": {
          "full_name": "pgadmin4",
          "args": {
            "appdir": "/Applications"
          }
        }
      },
      "zulip": {
        "version": "2.3.82",
        "options": {
          "args": {
            "appdir": "/Applications"
          }
        }
      },
      "postman": {
        "version": null,
        "options": {
          "full_name": "postman",
          "args": {
            "appdir": "/Applications"
          }
        }
      },
      "monodraw": {
        "version": "1.4,b103",
        "options": {
          "full_name": "monodraw",
          "args": {
            "appdir": "/Applications"
          }
        }
      },
      "kindlegen": {
        "version": "2.9",
        "options": {
          "full_name": "KindleGen",
          "args": {
            "appdir": "/Applications"
          }
        }
      },
      "basictex": {
        "version": "2019.1011",
        "options": {
          "full_name": "basictex",
          "args": {
            "appdir": "/Applications"
          }
        }
      },
      "sonos": {
        "version": "10.1",
        "options": {
          "full_name": "sonos",
          "args": {
            "appdir": "/Applications"
          }
        }
      },
      "focusrite-control": {
        "version": "3.5.0.1754",
        "options": {
          "full_name": "focusrite-control",
          "args": {
            "appdir": "/Applications"
          }
        }
      }
    },
    "mas": {
      "Fantastical 2": null,
      "Xcode": {
        "id": "497799835",
        "version": "11.3.1"
      },
      "Annotate": {
        "id": "918207447",
        "version": "2.1.4"
      },
      "Todoist": {
        "id": "585829637",
        "version": "7.2.6"
      },
      "Pixelmator": {
        "id": "407963104",
        "version": "3.9"
      },
      "Kindle": {
        "id": "405399194",
        "version": "1.28.0"
      },
      "MoneyMoney": {
        "id": "872698314",
        "version": "2.3.24"
      }
    }
  },
  "system": {
    "macos": {
      "mojave": {
        "HOMEBREW_VERSION": "2.2.12",
        "HOMEBREW_PREFIX": "/usr/local",
        "Homebrew/homebrew-core": "35893bb4a37f94127cd4727cdd664a0d97af91a2",
        "CLT": "10.3.0.0.1.1562985497",
        "Xcode": "11.3.1",
        "macOS": "10.14.6"
      }
    }
  }
}
